Terminalbrush/__init__.py
Terminalbrush/main.py
terminalbrush-0.2.4.dist-info/METADATA
terminalbrush-0.2.4.dist-info/WHEEL
terminalbrush-0.2.4.dist-info/top_level.txt
terminalbrush-0.2.4.dist-info/RECORD
