Metadata-Version: 2.1
Name: terminalbrush
Version: 0.2.4
Requires-Dist: requests
